white124/__init__.py
white124/main.py
white124-0.1.5.dist-info/LICENSE.txt
white124-0.1.5.dist-info/METADATA
white124-0.1.5.dist-info/WHEEL
white124-0.1.5.dist-info/top_level.txt
white124-0.1.5.dist-info/RECORD
