Metadata-Version: 2.1
Name: white124
Version: 0.1.5
Summary: Combining methods for convenience in new projects
Home-page: https://github.com/white124bk/
Author: Alexander White
Author-email: pip@mail83.ru
Classifier: Programming Language :: Python :: 3.9
Classifier: License :: OSI Approved :: MIT License
Classifier: Operating System :: OS Independent
Requires-Python: >=3.6
License-File: LICENSE.txt
Requires-Dist: pymysql
Requires-Dist: Dadata
